sandi_connect/__init__.py
sandi_connect/mqtt_connect.py
sandi_connect/IEEEC37118/__init__.py
sandi_connect/IEEEC37118/decode.py
sandi_connect-0.1.1.dist-info/METADATA
sandi_connect-0.1.1.dist-info/WHEEL
sandi_connect-0.1.1.dist-info/top_level.txt
sandi_connect-0.1.1.dist-info/RECORD
